nonebot_plugin_megumin/__init__.py
nonebot_plugin_megumin/charm.py
nonebot_plugin_megumin/config.py
nonebot_plugin_megumin/magic.py
nonebot_plugin_megumin/state.py
nonebot_plugin_megumin-0.2.6.dist-info/METADATA
nonebot_plugin_megumin-0.2.6.dist-info/WHEEL
nonebot_plugin_megumin-0.2.6.dist-info/RECORD
