Metadata-Version: 2.4
Name: nonebot_plugin_megumin
Version: 0.2.6
Summary: 现在，你的群友可以触发失传已久的爆裂魔法了！
Project-URL: Homepage, https://github.com/youlanan/nonebot_plugin_megumin
Project-URL: Repository, https://github.com/youlanan/nonebot_plugin_megumin.git
Project-URL: Documentation, https://github.com/youlanan/nonebot_plugin_megumin#readme
Author-email: youlanan <ylanan@foxmail.com>
License: MIT
Requires-Python: >=3.9
Requires-Dist: nonebot-plugin-alconna>=0.57.2
Requires-Dist: nonebot-plugin-localstore>=0.7.4
Requires-Dist: nonebot-plugin-uninfo>=0.7.3
Requires-Dist: nonebot2>=2.4.2
